{"3d眼镜":"https://cdn.jsdelivr.net/npm/sticker-heo@2022.7.5/Sticker-100/3d眼镜.png","EDG":"https://cdn.jsdelivr.net/npm/sticker-heo@2022.7.5/Sticker-100/EDG.png","LPL":"https://cdn.jsdelivr.net/npm/sticker-heo@2022.7.5/Sticker-100/LPL.png","beluga":"https://cdn.jsdelivr.net/npm/sticker-heo@2022.7.5/Sticker-100/beluga.png","不好意思":"https://cdn.jsdelivr.net/npm/sticker-heo@2022.7.5/Sticker-100/不好意思.png","不服吗":"https://cdn.jsdelivr.net/npm/sticker-heo@2022.7.5/Sticker-100/不服吗.png","亲亲":"https://cdn.jsdelivr.net/npm/sticker-heo@2022.7.5/Sticker-100/亲亲.png","伞兵":"https://cdn.jsdelivr.net/npm/sticker-heo@2022.7.5/Sticker-100/伞兵.png","倚墙笑":"https://cdn.jsdelivr.net/npm/sticker-heo@2022.7.5/Sticker-100/倚墙笑.png","值得肯定":"https://cdn.jsdelivr.net/npm/sticker-heo@2022.7.5/Sticker-100/值得肯定.png","偷偷看":"https://cdn.jsdelivr.net/npm/sticker-heo@2022.7.5/Sticker-100/偷偷看.png","傻笑":"https://cdn.jsdelivr.net/npm/sticker-heo@2022.7.5/Sticker-100/傻笑.png","再见":"https://cdn.jsdelivr.net/npm/sticker-heo@2022.7.5/Sticker-100/再见.png","出家人":"https://cdn.jsdelivr.net/npm/sticker-heo@2022.7.5/Sticker-100/出家人.png","击剑":"https://cdn.jsdelivr.net/npm/sticker-heo@2022.7.5/Sticker-100/击剑.png","加班":"https://cdn.jsdelivr.net/npm/sticker-heo@2022.7.5/Sticker-100/加班.png","勉强笑":"https://cdn.jsdelivr.net/npm/sticker-heo@2022.7.5/Sticker-100/勉强笑.png","危险":"https://cdn.jsdelivr.net/npm/sticker-heo@2022.7.5/Sticker-100/危险.png","发红包":"https://cdn.jsdelivr.net/npm/sticker-heo@2022.7.5/Sticker-100/发红包.png","吃手":"https://cdn.jsdelivr.net/npm/sticker-heo@2022.7.5/Sticker-100/吃手.png","吃瓜":"https://cdn.jsdelivr.net/npm/sticker-heo@2022.7.5/Sticker-100/吃瓜.png","吐血":"https://cdn.jsdelivr.net/npm/sticker-heo@2022.7.5/Sticker-100/吐血.png","吵架":"https://cdn.jsdelivr.net/npm/sticker-heo@2022.7.5/Sticker-100/吵架.png","呦吼":"https://cdn.jsdelivr.net/npm/sticker-heo@2022.7.5/Sticker-100/呦吼.png","呲牙笑":"https://cdn.jsdelivr.net/npm/sticker-heo@2022.7.5/Sticker-100/呲牙笑.png","哈士奇":"https://cdn.jsdelivr.net/npm/sticker-heo@2022.7.5/Sticker-100/哈士奇.png","哈士奇失去意识":"https://cdn.jsdelivr.net/npm/sticker-heo@2022.7.5/Sticker-100/哈士奇失去意识.png","哈士奇失望":"https://cdn.jsdelivr.net/npm/sticker-heo@2022.7.5/Sticker-100/哈士奇失望.png","哭泣":"https://cdn.jsdelivr.net/npm/sticker-heo@2022.7.5/Sticker-100/哭泣.png","唱歌":"https://cdn.jsdelivr.net/npm/sticker-heo@2022.7.5/Sticker-100/唱歌.png","喜欢":"https://cdn.jsdelivr.net/npm/sticker-heo@2022.7.5/Sticker-100/喜欢.png","嘿哈":"https://cdn.jsdelivr.net/npm/sticker-heo@2022.7.5/Sticker-100/嘿哈.png","大笑":"https://cdn.jsdelivr.net/npm/sticker-heo@2022.7.5/Sticker-100/大笑.png","失去信号":"https://cdn.jsdelivr.net/npm/sticker-heo@2022.7.5/Sticker-100/失去信号.png","失望":"https://cdn.jsdelivr.net/npm/sticker-heo@2022.7.5/Sticker-100/失望.png","头秃":"https://cdn.jsdelivr.net/npm/sticker-heo@2022.7.5/Sticker-100/头秃.png","奋斗":"https://cdn.jsdelivr.net/npm/sticker-heo@2022.7.5/Sticker-100/奋斗.png","好奇":"https://cdn.jsdelivr.net/npm/sticker-heo@2022.7.5/Sticker-100/好奇.png","好的":"https://cdn.jsdelivr.net/npm/sticker-heo@2022.7.5/Sticker-100/好的.png","害羞":"https://cdn.jsdelivr.net/npm/sticker-heo@2022.7.5/Sticker-100/害羞.png","小丑":"https://cdn.jsdelivr.net/npm/sticker-heo@2022.7.5/Sticker-100/小丑.png","小偷":"https://cdn.jsdelivr.net/npm/sticker-heo@2022.7.5/Sticker-100/小偷.png","尬笑":"https://cdn.jsdelivr.net/npm/sticker-heo@2022.7.5/Sticker-100/尬笑.png","尴尬":"https://cdn.jsdelivr.net/npm/sticker-heo@2022.7.5/Sticker-100/尴尬.png","应援":"https://cdn.jsdelivr.net/npm/sticker-heo@2022.7.5/Sticker-100/应援.png","开心":"https://cdn.jsdelivr.net/npm/sticker-heo@2022.7.5/Sticker-100/开心.png","引起不适":"https://cdn.jsdelivr.net/npm/sticker-heo@2022.7.5/Sticker-100/引起不适.png","微笑":"https://cdn.jsdelivr.net/npm/sticker-heo@2022.7.5/Sticker-100/微笑.png","思考":"https://cdn.jsdelivr.net/npm/sticker-heo@2022.7.5/Sticker-100/思考.png","恶心":"https://cdn.jsdelivr.net/npm/sticker-heo@2022.7.5/Sticker-100/恶心.png","恶魔":"https://cdn.jsdelivr.net/npm/sticker-heo@2022.7.5/Sticker-100/恶魔.png","恶魔恐惧":"https://cdn.jsdelivr.net/npm/sticker-heo@2022.7.5/Sticker-100/恶魔恐惧.png","惊吓":"https://cdn.jsdelivr.net/npm/sticker-heo@2022.7.5/Sticker-100/惊吓.png","惊吓白眼":"https://cdn.jsdelivr.net/npm/sticker-heo@2022.7.5/Sticker-100/惊吓白眼.png","惊讶":"https://cdn.jsdelivr.net/npm/sticker-heo@2022.7.5/Sticker-100/惊讶.png","惬意":"https://cdn.jsdelivr.net/npm/sticker-heo@2022.7.5/Sticker-100/惬意.png","感动":"https://cdn.jsdelivr.net/npm/sticker-heo@2022.7.5/Sticker-100/感动.png","愤怒":"https://cdn.jsdelivr.net/npm/sticker-heo@2022.7.5/Sticker-100/愤怒.png","我看好你":"https://cdn.jsdelivr.net/npm/sticker-heo@2022.7.5/Sticker-100/我看好你.png","手机相机":"https://cdn.jsdelivr.net/npm/sticker-heo@2022.7.5/Sticker-100/手机相机.png","打咩":"https://cdn.jsdelivr.net/npm/sticker-heo@2022.7.5/Sticker-100/打咩.png","打牌":"https://cdn.jsdelivr.net/npm/sticker-heo@2022.7.5/Sticker-100/打牌.png","托腮":"https://cdn.jsdelivr.net/npm/sticker-heo@2022.7.5/Sticker-100/托腮.png","扶额":"https://cdn.jsdelivr.net/npm/sticker-heo@2022.7.5/Sticker-100/扶额.png","抠鼻":"https://cdn.jsdelivr.net/npm/sticker-heo@2022.7.5/Sticker-100/抠鼻.png","抬眼镜":"https://cdn.jsdelivr.net/npm/sticker-heo@2022.7.5/Sticker-100/抬眼镜.png","拜托":"https://cdn.jsdelivr.net/npm/sticker-heo@2022.7.5/Sticker-100/拜托.png","捂嘴笑":"https://cdn.jsdelivr.net/npm/sticker-heo@2022.7.5/Sticker-100/捂嘴笑.png","捂脸":"https://cdn.jsdelivr.net/npm/sticker-heo@2022.7.5/Sticker-100/捂脸.png","擦汗":"https://cdn.jsdelivr.net/npm/sticker-heo@2022.7.5/Sticker-100/擦汗.png","放鞭炮":"https://cdn.jsdelivr.net/npm/sticker-heo@2022.7.5/Sticker-100/放鞭炮.png","敬礼":"https://cdn.jsdelivr.net/npm/sticker-heo@2022.7.5/Sticker-100/敬礼.png","整理发型":"https://cdn.jsdelivr.net/npm/sticker-heo@2022.7.5/Sticker-100/整理发型.png","斗鸡眼":"https://cdn.jsdelivr.net/npm/sticker-heo@2022.7.5/Sticker-100/斗鸡眼.png","智慧的眼神":"https://cdn.jsdelivr.net/npm/sticker-heo@2022.7.5/Sticker-100/智慧的眼神.png","月饼":"https://cdn.jsdelivr.net/npm/sticker-heo@2022.7.5/Sticker-100/月饼.png","有没有搞错":"https://cdn.jsdelivr.net/npm/sticker-heo@2022.7.5/Sticker-100/有没有搞错.png","正确":"https://cdn.jsdelivr.net/npm/sticker-heo@2022.7.5/Sticker-100/正确.png","没招":"https://cdn.jsdelivr.net/npm/sticker-heo@2022.7.5/Sticker-100/没招.png","波吉":"https://cdn.jsdelivr.net/npm/sticker-heo@2022.7.5/Sticker-100/波吉.png","泪奔":"https://cdn.jsdelivr.net/npm/sticker-heo@2022.7.5/Sticker-100/泪奔.png","流汗微笑":"https://cdn.jsdelivr.net/npm/sticker-heo@2022.7.5/Sticker-100/流汗微笑.png","流鼻涕":"https://cdn.jsdelivr.net/npm/sticker-heo@2022.7.5/Sticker-100/流鼻涕.png","深思":"https://cdn.jsdelivr.net/npm/sticker-heo@2022.7.5/Sticker-100/深思.png","滑稽":"https://cdn.jsdelivr.net/npm/sticker-heo@2022.7.5/Sticker-100/滑稽.png","滑稽吃瓜":"https://cdn.jsdelivr.net/npm/sticker-heo@2022.7.5/Sticker-100/滑稽吃瓜.png","滑稽喝水":"https://cdn.jsdelivr.net/npm/sticker-heo@2022.7.5/Sticker-100/滑稽喝水.png","滑稽奶茶":"https://cdn.jsdelivr.net/npm/sticker-heo@2022.7.5/Sticker-100/滑稽奶茶.png","滑稽柠檬":"https://cdn.jsdelivr.net/npm/sticker-heo@2022.7.5/Sticker-100/滑稽柠檬.png","滑稽狂汗":"https://cdn.jsdelivr.net/npm/sticker-heo@2022.7.5/Sticker-100/滑稽狂汗.png","滑稽被子":"https://cdn.jsdelivr.net/npm/sticker-heo@2022.7.5/Sticker-100/滑稽被子.png","烦恼":"https://cdn.jsdelivr.net/npm/sticker-heo@2022.7.5/Sticker-100/烦恼.png","熊熊":"https://cdn.jsdelivr.net/npm/sticker-heo@2022.7.5/Sticker-100/熊熊.png","熊猫":"https://cdn.jsdelivr.net/npm/sticker-heo@2022.7.5/Sticker-100/熊猫.png","熊猫唱歌":"https://cdn.jsdelivr.net/npm/sticker-heo@2022.7.5/Sticker-100/熊猫唱歌.png","熊猫喜欢":"https://cdn.jsdelivr.net/npm/sticker-heo@2022.7.5/Sticker-100/熊猫喜欢.png","熊猫失望":"https://cdn.jsdelivr.net/npm/sticker-heo@2022.7.5/Sticker-100/熊猫失望.png","熊猫意外":"https://cdn.jsdelivr.net/npm/sticker-heo@2022.7.5/Sticker-100/熊猫意外.png","熬夜":"https://cdn.jsdelivr.net/npm/sticker-heo@2022.7.5/Sticker-100/熬夜.png","爆炸":"https://cdn.jsdelivr.net/npm/sticker-heo@2022.7.5/Sticker-100/爆炸.png","牛年进宝":"https://cdn.jsdelivr.net/npm/sticker-heo@2022.7.5/Sticker-100/牛年进宝.png","狂热":"https://cdn.jsdelivr.net/npm/sticker-heo@2022.7.5/Sticker-100/狂热.png","狗头":"https://cdn.jsdelivr.net/npm/sticker-heo@2022.7.5/Sticker-100/狗头.png","狗头围脖":"https://cdn.jsdelivr.net/npm/sticker-heo@2022.7.5/Sticker-100/狗头围脖.png","狗头失望":"https://cdn.jsdelivr.net/npm/sticker-heo@2022.7.5/Sticker-100/狗头失望.png","狗头意外":"https://cdn.jsdelivr.net/npm/sticker-heo@2022.7.5/Sticker-100/狗头意外.png","狗头胖次":"https://cdn.jsdelivr.net/npm/sticker-heo@2022.7.5/Sticker-100/狗头胖次.png","狗头花":"https://cdn.jsdelivr.net/npm/sticker-heo@2022.7.5/Sticker-100/狗头花.png","狗头草":"https://cdn.jsdelivr.net/npm/sticker-heo@2022.7.5/Sticker-100/狗头草.png","猪头":"https://cdn.jsdelivr.net/npm/sticker-heo@2022.7.5/Sticker-100/猪头.png","猪头意外":"https://cdn.jsdelivr.net/npm/sticker-heo@2022.7.5/Sticker-100/猪头意外.png","生病":"https://cdn.jsdelivr.net/npm/sticker-heo@2022.7.5/Sticker-100/生病.png","电话":"https://cdn.jsdelivr.net/npm/sticker-heo@2022.7.5/Sticker-100/电话.png","疑问":"https://cdn.jsdelivr.net/npm/sticker-heo@2022.7.5/Sticker-100/疑问.png","疼痛":"https://cdn.jsdelivr.net/npm/sticker-heo@2022.7.5/Sticker-100/疼痛.png","痛哭":"https://cdn.jsdelivr.net/npm/sticker-heo@2022.7.5/Sticker-100/痛哭.png","看穿一切":"https://cdn.jsdelivr.net/npm/sticker-heo@2022.7.5/Sticker-100/看穿一切.png","眩晕":"https://cdn.jsdelivr.net/npm/sticker-heo@2022.7.5/Sticker-100/眩晕.png","睡觉":"https://cdn.jsdelivr.net/npm/sticker-heo@2022.7.5/Sticker-100/睡觉.png","禁言":"https://cdn.jsdelivr.net/npm/sticker-heo@2022.7.5/Sticker-100/禁言.png","笑哭":"https://cdn.jsdelivr.net/npm/sticker-heo@2022.7.5/Sticker-100/笑哭.png","纠结":"https://cdn.jsdelivr.net/npm/sticker-heo@2022.7.5/Sticker-100/纠结.png","绿帽":"https://cdn.jsdelivr.net/npm/sticker-heo@2022.7.5/Sticker-100/绿帽.png","缺牙笑":"https://cdn.jsdelivr.net/npm/sticker-heo@2022.7.5/Sticker-100/缺牙笑.png","翻白眼":"https://cdn.jsdelivr.net/npm/sticker-heo@2022.7.5/Sticker-100/翻白眼.png","老虎意外":"https://cdn.jsdelivr.net/npm/sticker-heo@2022.7.5/Sticker-100/老虎意外.png","耍酷":"https://cdn.jsdelivr.net/npm/sticker-heo@2022.7.5/Sticker-100/耍酷.png","胡子":"https://cdn.jsdelivr.net/npm/sticker-heo@2022.7.5/Sticker-100/胡子.png","菜狗":"https://cdn.jsdelivr.net/npm/sticker-heo@2022.7.5/Sticker-100/菜狗.png","菜狗花":"https://cdn.jsdelivr.net/npm/sticker-heo@2022.7.5/Sticker-100/菜狗花.png","蒙面滑稽":"https://cdn.jsdelivr.net/npm/sticker-heo@2022.7.5/Sticker-100/蒙面滑稽.png","虎年进宝":"https://cdn.jsdelivr.net/npm/sticker-heo@2022.7.5/Sticker-100/虎年进宝.png","被打":"https://cdn.jsdelivr.net/npm/sticker-heo@2022.7.5/Sticker-100/被打.png","裂开":"https://cdn.jsdelivr.net/npm/sticker-heo@2022.7.5/Sticker-100/裂开.png","警告":"https://cdn.jsdelivr.net/npm/sticker-heo@2022.7.5/Sticker-100/警告.png","读书":"https://cdn.jsdelivr.net/npm/sticker-heo@2022.7.5/Sticker-100/读书.png","财神红包":"https://cdn.jsdelivr.net/npm/sticker-heo@2022.7.5/Sticker-100/财神红包.png","超爱":"https://cdn.jsdelivr.net/npm/sticker-heo@2022.7.5/Sticker-100/超爱.png","这是啥":"https://cdn.jsdelivr.net/npm/sticker-heo@2022.7.5/Sticker-100/这是啥.png","送福":"https://cdn.jsdelivr.net/npm/sticker-heo@2022.7.5/Sticker-100/送福.png","送花":"https://cdn.jsdelivr.net/npm/sticker-heo@2022.7.5/Sticker-100/送花.png","错误":"https://cdn.jsdelivr.net/npm/sticker-heo@2022.7.5/Sticker-100/错误.png","阴险":"https://cdn.jsdelivr.net/npm/sticker-heo@2022.7.5/Sticker-100/阴险.png","难以置信":"https://cdn.jsdelivr.net/npm/sticker-heo@2022.7.5/Sticker-100/难以置信.png","面具":"https://cdn.jsdelivr.net/npm/sticker-heo@2022.7.5/Sticker-100/面具.png","饥渴":"https://cdn.jsdelivr.net/npm/sticker-heo@2022.7.5/Sticker-100/饥渴.png","鬼脸":"https://cdn.jsdelivr.net/npm/sticker-heo@2022.7.5/Sticker-100/鬼脸.png","黑线":"https://cdn.jsdelivr.net/npm/sticker-heo@2022.7.5/Sticker-100/黑线.png","鼓掌":"https://cdn.jsdelivr.net/npm/sticker-heo@2022.7.5/Sticker-100/鼓掌.png"}